socpi/__init__.py
socpi/__main__.py
socpi/app.py
socpi/client.py
socpi/message.py
socpi/request.py
socpi/utils.py
socpi-0.2.1.dist-info/LICENSE
socpi-0.2.1.dist-info/WHEEL
socpi-0.2.1.dist-info/METADATA
socpi-0.2.1.dist-info/RECORD
