Metadata-Version: 2.1
Name: socpi
Version: 0.2.1
Summary: A simple socket api framework
Home-page: https://github.com/HakierGrzonzo/socpi
License: GPLv2
Keywords: sockets,asyncio
Author: Grzegorz Koperwas
Author-email: admin@grzegorzkoperwas.site
Requires-Python: >=3.10,<4.0
Classifier: Development Status :: 2 - Pre-Alpha
Classifier: Intended Audience :: Developers
Classifier: License :: OSI Approved :: GNU General Public License v2 (GPLv2)
Classifier: License :: Other/Proprietary License
Classifier: Operating System :: Unix
Classifier: Programming Language :: Python :: 3
Classifier: Programming Language :: Python :: 3.10
Project-URL: Repository, https://github.com/HakierGrzonzo/socpi
